setup.py
clusterone/__init__.py
clusterone/auth.py
clusterone/client_exceptions.py
clusterone/clusterone_cli.py
clusterone/clusterone_client.py
clusterone/config.py
clusterone/functional_check.py
clusterone/instances.py
clusterone/messages.py
clusterone/test_exceptions.py
clusterone/test_main.py
clusterone/test_programatic.py
clusterone/tf_runner.py
clusterone/utils.py
clusterone/version.py
clusterone/commands/__init__.py
clusterone/commands/create/__init__.py
clusterone/commands/create/dataset/__init__.py
clusterone/commands/create/dataset/cmd.py
clusterone/commands/create/dataset/test_cmd.py
clusterone/commands/create/job/__init__.py
clusterone/commands/create/job/base_cmd.py
clusterone/commands/create/job/distributed.py
clusterone/commands/create/job/single.py
clusterone/commands/create/job/test_base_cmd.py
clusterone/commands/create/job/test_distributed.py
clusterone/commands/create/job/test_single.py
clusterone/commands/create/project/__init__.py
clusterone/commands/create/project/cmd.py
clusterone/commands/create/project/helper.py
clusterone/commands/create/project/test_cmd.py
clusterone/commands/create/project/test_helper.py
clusterone/commands/get/__init__.py
clusterone/commands/get/job/__init__.py
clusterone/commands/get/job/cmd.py
clusterone/commands/get/job/test_cmd.py
clusterone/commands/get/project/__init__.py
clusterone/commands/get/project/cmd.py
clusterone/commands/get/project/test_cmd.py
clusterone/commands/init/__init__.py
clusterone/commands/init/project/__init__.py
clusterone/commands/init/project/cmd.py
clusterone/commands/init/project/test_cmd.py
clusterone/commands/ln/__init__.py
clusterone/commands/ln/dataset/__init__.py
clusterone/commands/ln/dataset/cmd.py
clusterone/commands/ln/dataset/helper.py
clusterone/commands/ln/dataset/test_cmd.py
clusterone/commands/ln/dataset/test_helper.py
clusterone/commands/ln/project/__init__.py
clusterone/commands/ln/project/cmd.py
clusterone/commands/ln/project/helper.py
clusterone_test.egg-info/PKG-INFO
clusterone_test.egg-info/SOURCES.txt
clusterone_test.egg-info/dependency_links.txt
clusterone_test.egg-info/entry_points.txt
clusterone_test.egg-info/requires.txt
clusterone_test.egg-info/top_level.txt